LICENSE
README.md
pyproject.toml
src/lima2mxh5master/__init__.py
src/lima2mxh5master.egg-info/PKG-INFO
src/lima2mxh5master.egg-info/SOURCES.txt
src/lima2mxh5master.egg-info/dependency_links.txt
src/lima2mxh5master.egg-info/requires.txt
src/lima2mxh5master.egg-info/top_level.txt
src/lima2mxh5master/api/__init__.py
src/lima2mxh5master/api/api_convert_lima1_to_h5mx.py
src/lima2mxh5master/api/api_convert_lima2_to_h5mx.py
src/lima2mxh5master/api/api_dump_dict_to_nx.py
src/lima2mxh5master/core/__init__.py
src/lima2mxh5master/core/build_context_from_schema.py
src/lima2mxh5master/core/pydantic_models.py
src/lima2mxh5master/core/refactor_external_h5dict.py
src/lima2mxh5master/core/refactor_internal_h5dict.py
src/lima2mxh5master/profiles/loader.py
src/lima2mxh5master/profiles/lima1_to_h5mx/__init__.py
src/lima2mxh5master/profiles/lima1_to_h5mx/handlers_lima1_to_h5mx.py
src/lima2mxh5master/profiles/lima1_to_h5mx/schema_lima1_to_h5mx.json
src/lima2mxh5master/profiles/lima2_to_h5mx/__init__.py
src/lima2mxh5master/profiles/lima2_to_h5mx/handlers_lima2_to_h5mx.py
src/lima2mxh5master/profiles/lima2_to_h5mx/schema_lima2_to_h5mx.json
tests/test_core_api.py
tests/test_profiles_api.py